.gitignore
LICENSE
README.md
requirements.txt
setup.py
grammar_text/__init__.py
grammar_text/admin.py
grammar_text/consts.py
grammar_text/forms.py
grammar_text/models.py
grammar_text/serializers.py
grammar_text/urls.py
grammar_text/views.py
grammar_text.egg-info/PKG-INFO
grammar_text.egg-info/SOURCES.txt
grammar_text.egg-info/dependency_links.txt
grammar_text.egg-info/requires.txt
grammar_text.egg-info/top_level.txt
grammar_text/migrations/0001_initial.py
grammar_text/migrations/0002_auto_20160720_0459.py
grammar_text/migrations/__init__.py
grammar_text/static/grammar_text/main.coffee
grammar_text/static/grammar_text/main.css
grammar_text/static/grammar_text/main.js
grammar_text/templates/grammar_text/widget.html