Metadata-Version: 1.0
Name: grammar-text
Version: 0.0.4
Summary: Text with grammar.
Home-page: https://github.com/telminov/grammar-text
Author: Telminov Sergey
Author-email: sergey@telminov.ru
License: The MIT License
Platform: UNKNOWN
